django_maker/__init__.py
django_maker/admin.py
django_maker/apps.py
django_maker/models.py
django_maker/tests.py
django_maker/views.py
django_maker/management/commands/create_models.py
django_maker/management/commands/create_serializer.py
django_maker/management/commands/create_simple_CRUD.py
django_maker/management/commands/createapp.py
django_maker/management/commands/find_model.py
django_maker/management/commands/function.py
django_maker/migrations/__init__.py
maker_django/__init__.py
maker_django/asgi.py
maker_django/settings.py
maker_django/urls.py
maker_django/wsgi.py
django_maker-2.0.0.dist-info/METADATA
django_maker-2.0.0.dist-info/WHEEL
django_maker-2.0.0.dist-info/top_level.txt
django_maker-2.0.0.dist-info/RECORD
