Metadata-Version: 2.4
Name: django_maker
Version: 2.0.0
Summary: A Python package for managing framework django
Requires-Dist: Django>=3.0
Dynamic: description
Dynamic: description-content-type
Dynamic: requires-dist
Dynamic: summary
